{
    "type": "gif",
    "id": "26BRCrcorsBKx0Hw4",
    "slug": "sporzaredactie-ronaldo-cristiano-sporza-26BRCrcorsBKx0Hw4",
    "url": "https://giphy.com/gifs/sporzaredactie-ronaldo-cristiano-sporza-26BRCrcorsBKx0Hw4",
    "bitly_gif_url": "https://gph.is/29x2Zic",
    "bitly_url": "https://gph.is/29x2Zic",
    "embed_url": "https://giphy.com/embed/26BRCrcorsBKx0Hw4",
    "username": "sporzaredactie",
    "source": "",
    "rating": "g",
    "content_url": "",
    "source_tld": "",
    "source_post_url": "",
    "is_sticker": 0,
    "import_datetime": "2016-07-11 05:23:17",
    "trending_datetime": "0000-00-00 00:00:00",
    "user": {
        "avatar_url": "https://media.giphy.com/avatars/sporzaredactie/e3oxkvg1wYNm.png",
        "banner_url": "https://media.giphy.com/headers/sporzaredactie/gtUML7UmiYBt.png",
        "profile_url": "https://giphy.com/sporzaredactie/",
        "username": "sporzaredactie",
        "display_name": "Sporza",
        "guid": "c3BvcnphcmVkYWN0aWVAZ21haWwuY29t"
    },
    "images": {
        "fixed_height_still": {
            "url": "https://media2.giphy.com/media/26BRCrcorsBKx0Hw4/200_s.gif",
            "width": "366",
            "height": "200"
        },
        "original_still": {
            "url": "https://media2.giphy.com/media/26BRCrcorsBKx0Hw4/giphy_s.gif",
            "width": "480",
            "height": "262"
        },
        "fixed_width": {
            "url": "https://media2.giphy.com/media/26BRCrcorsBKx0Hw4/200w.gif",
            "width": "200",
            "height": "109",
            "size": "813336",
            "mp4": "https://media2.giphy.com/media/26BRCrcorsBKx0Hw4/200w.mp4",
            "mp4_size": "42837",
            "webp": "https://media2.giphy.com/media/26BRCrcorsBKx0Hw4/200w.webp",
            "webp_size": "260366"
        },
        "fixed_height_small_still": {
            "url": "https://media2.giphy.com/media/26BRCrcorsBKx0Hw4/100_s.gif",
            "width": "183",
            "height": "100"
        },
        "fixed_height_downsampled": {
            "url": "https://media2.giphy.com/media/26BRCrcorsBKx0Hw4/200_d.gif",
            "width": "366",
            "height": "200",
            "size": "332663",
            "webp": "https://media2.giphy.com/media/26BRCrcorsBKx0Hw4/200_d.webp",
            "webp_size": "79496"
        },
        "preview": {
            "width": "290",
            "height": "158",
            "mp4": "https://media2.giphy.com/media/26BRCrcorsBKx0Hw4/giphy-preview.mp4",
            "mp4_size": "39965"
        },
        "fixed_height_small": {
            "url": "https://media2.giphy.com/media/26BRCrcorsBKx0Hw4/100.gif",
            "width": "183",
            "height": "100",
            "size": "715375",
            "mp4": "https://media2.giphy.com/media/26BRCrcorsBKx0Hw4/100.mp4",
            "mp4_size": "37836",
            "webp": "https://media2.giphy.com/media/26BRCrcorsBKx0Hw4/100.webp",
            "webp_size": "238620"
        },
        "downsized_still": {
            "url": "https://media2.giphy.com/media/26BRCrcorsBKx0Hw4/giphy-downsized_s.gif",
            "width": "250",
            "height": "136",
            "size": "26659"
        },
        "downsized": {
            "url": "https://media2.giphy.com/media/26BRCrcorsBKx0Hw4/giphy-downsized.gif",
            "width": "250",
            "height": "136",
            "size": "1214082"
        },
        "downsized_large": {
            "url": "https://media2.giphy.com/media/26BRCrcorsBKx0Hw4/giphy.gif",
            "width": "480",
            "height": "262",
            "size": "4354447"
        },
        "fixed_width_small_still": {
            "url": "https://media2.giphy.com/media/26BRCrcorsBKx0Hw4/100w_s.gif",
            "width": "100",
            "height": "55"
        },
        "preview_webp": {
            "url": "https://media2.giphy.com/media/26BRCrcorsBKx0Hw4/giphy-preview.webp",
            "width": "191",
            "height": "104",
            "size": "48232"
        },
        "fixed_width_still": {
            "url": "https://media2.giphy.com/media/26BRCrcorsBKx0Hw4/200w_s.gif",
            "width": "200",
            "height": "109"
        },
        "fixed_width_small": {
            "url": "https://media2.giphy.com/media/26BRCrcorsBKx0Hw4/100w.gif",
            "width": "100",
            "height": "55",
            "size": "237342",
            "mp4": "https://media2.giphy.com/media/26BRCrcorsBKx0Hw4/100w.mp4",
            "mp4_size": "17409",
            "webp": "https://media2.giphy.com/media/26BRCrcorsBKx0Hw4/100w.webp",
            "webp_size": "99874"
        },
        "downsized_small": {
            "width": "480",
            "height": "262",
            "mp4": "https://media2.giphy.com/media/26BRCrcorsBKx0Hw4/giphy-downsized-small.mp4",
            "mp4_size": "191049"
        },
        "fixed_width_downsampled": {
            "url": "https://media2.giphy.com/media/26BRCrcorsBKx0Hw4/200w_d.gif",
            "width": "200",
            "height": "109",
            "size": "111788",
            "webp": "https://media2.giphy.com/media/26BRCrcorsBKx0Hw4/200w_d.webp",
            "webp_size": "32838"
        },
        "downsized_medium": {
            "url": "https://media2.giphy.com/media/26BRCrcorsBKx0Hw4/giphy.gif",
            "width": "480",
            "height": "262",
            "size": "4354447"
        },
        "original": {
            "url": "https://media2.giphy.com/media/26BRCrcorsBKx0Hw4/giphy.gif",
            "width": "480",
            "height": "262",
            "size": "4354447",
            "frames": "47",
            "mp4": "https://media2.giphy.com/media/26BRCrcorsBKx0Hw4/giphy.mp4",
            "mp4_size": "187542",
            "webp": "https://media2.giphy.com/media/26BRCrcorsBKx0Hw4/giphy.webp",
            "webp_size": "1019714"
        },
        "fixed_height": {
            "url": "https://media2.giphy.com/media/26BRCrcorsBKx0Hw4/200.gif",
            "width": "366",
            "height": "200",
            "size": "2491146",
            "mp4": "https://media2.giphy.com/media/26BRCrcorsBKx0Hw4/200.mp4",
            "mp4_size": "98532",
            "webp": "https://media2.giphy.com/media/26BRCrcorsBKx0Hw4/200.webp",
            "webp_size": "628592"
        },
        "looping": {
            "mp4": "https://media2.giphy.com/media/26BRCrcorsBKx0Hw4/giphy-loop.mp4",
            "mp4_size": "1323519"
        },
        "original_mp4": {
            "width": "480",
            "height": "262",
            "mp4": "https://media2.giphy.com/media/26BRCrcorsBKx0Hw4/giphy.mp4",
            "mp4_size": "187542"
        },
        "preview_gif": {
            "url": "https://media2.giphy.com/media/26BRCrcorsBKx0Hw4/giphy-preview.gif",
            "width": "104",
            "height": "57",
            "size": "48593"
        },
        "480w_still": {
            "url": "https://media1.giphy.com/media/26BRCrcorsBKx0Hw4/480w_s.jpg",
            "width": "480",
            "height": "262"
        }
    },
    "title": "euro 2016 cristiano GIF by Sporza",
    "_score": 2500023.2
}

